bashcolor/__init__.py
bashcolor-1.1.1.dist-info/METADATA
bashcolor-1.1.1.dist-info/WHEEL
bashcolor-1.1.1.dist-info/entry_points.txt
bashcolor-1.1.1.dist-info/top_level.txt
bashcolor-1.1.1.dist-info/RECORD
