Metadata-Version: 2.1
Name: bashcolor
Version: 1.1.1
Summary: A simple library to get colors in the bash terminal
Home-page: https://github.com/sbrunner/bashcolor/
Author: Stéphane Brunner
Author-email: stephane.brunner@gmail.com
License: UNKNOWN
Platform: UNKNOWN
Classifier: Development Status :: 5 - Production/Stable
Classifier: Intended Audience :: Developers
Classifier: License :: OSI Approved :: BSD License
Classifier: Operating System :: OS Independent
Classifier: Programming Language :: Python
Classifier: Programming Language :: Python :: 3
Classifier: Programming Language :: Python :: 3.8
Classifier: Typing :: Typed
